autoextract/__init__.py
autoextract/__main__.py
autoextract/__version__.py
autoextract/apikey.py
autoextract/batching.py
autoextract/constants.py
autoextract/request.py
autoextract/stats.py
autoextract/sync.py
autoextract/utils.py
autoextract/aio/__init__.py
autoextract/aio/client.py
autoextract/aio/errors.py
autoextract/aio/retry.py
zyte_autoextract-0.7.1.dist-info/LICENSE
zyte_autoextract-0.7.1.dist-info/METADATA
zyte_autoextract-0.7.1.dist-info/WHEEL
zyte_autoextract-0.7.1.dist-info/top_level.txt
zyte_autoextract-0.7.1.dist-info/RECORD
