Metadata-Version: 2.1
Name: zyte-autoextract
Version: 0.7.1
Summary: Python interface to Zyte Automatic Extraction API
Home-page: https://github.com/zytedata/zyte-autoextract
Author: Mikhail Korobov
Author-email: kmike84@gmail.com
License: UNKNOWN
Platform: UNKNOWN
Classifier: Development Status :: 3 - Alpha
Classifier: Intended Audience :: Developers
Classifier: License :: OSI Approved :: BSD License
Classifier: Natural Language :: English
Classifier: Operating System :: OS Independent
Classifier: Programming Language :: Python :: 3
Classifier: Programming Language :: Python :: 3.5
Classifier: Programming Language :: Python :: 3.6
Classifier: Programming Language :: Python :: 3.7
Classifier: Programming Language :: Python :: 3.8
Classifier: Programming Language :: Python :: 3.9
License-File: LICENSE
Requires-Dist: requests
Requires-Dist: attrs
Requires-Dist: runstats
Requires-Dist: tenacity ; python_version >= "3.6"
Requires-Dist: aiohttp (>=3.6.0) ; python_version >= "3.6"
Requires-Dist: tqdm ; python_version >= "3.6"
